enocean/__init__.py
enocean/consolelogger.py
enocean/utils.py
enocean/communicators/__init__.py
enocean/communicators/communicator.py
enocean/communicators/serialcommunicator.py
enocean/communicators/tcpcommunicator.py
enocean/communicators/utils.py
enocean/protocol/EEP.xml
enocean/protocol/__init__.py
enocean/protocol/constants.py
enocean/protocol/crc8.py
enocean/protocol/eep.py
enocean/protocol/packet.py
enocean4ha-0.71.0.dist-info/LICENSE
enocean4ha-0.71.0.dist-info/METADATA
enocean4ha-0.71.0.dist-info/WHEEL
enocean4ha-0.71.0.dist-info/top_level.txt
enocean4ha-0.71.0.dist-info/RECORD
