Metadata-Version: 2.1
Name: enocean4ha
Version: 0.71.0
Summary: EnOcean serial protocol implementation
Author-email: Kimmo Huoman <kipenroskaposti@gmail.com>
Maintainer-email: Torsten Pieper <topic2k@atlogger.de>
Project-URL: Homepage, https://github.com/topic2k/enocean4ha
Project-URL: Issues, https://github.com/topic2k/enocean4ha/issues
Keywords: EnOcean,HomeAssistant
Classifier: Programming Language :: Python :: 3
Classifier: License :: OSI Approved :: MIT License
Classifier: Operating System :: OS Independent
Classifier: Intended Audience :: Developers
Classifier: Topic :: Home Automation
Requires-Python: >=3.9
License-File: LICENSE
Requires-Dist: pyserial >=3.5
Requires-Dist: beautifulsoup4 >=4.12
Requires-Dist: lxml >=5.3
Provides-Extra: tests
Requires-Dist: nose2 >=0.15.1 ; extra == 'tests'
